{
  "propertyGroup": 1,
  "propertyDescription": "Bán nhà mặt tiền đường số 2 cư xá Đô Thành, phường 4, quận 3. DT: 4,3x22m. XD 1 trệt 4 lầu, nhà đẹp và mới đang cho thuê giá cao, có hẻm sau. Khu vực an ninh, dân trí cao, xung quanh là các tòa nhà văn phòng, trung tâm tiếng anh, siêu thị\u2026 Rất lý tưởng để ở hoặc kinh doanh. Nay gia đình cần bán gấp với giá 12,5 tỷ. Xem nhà vui lòng LH: Bùi Tuấn: 091 66 333 79.",
  "propertyAddress": "Đường 2 Cư xá Đô Thành, Quận 3, Hồ Chí Minh",
  "propertyMobile": "0916633379",
  "propertySquare": "94.6m²",
  "propertyExpired": "18-01-2016",
  "propertyEmail": "saigoncentre002@gmail.com",
  "propertyPosted": "13-01-2016",
  "propertyUrl": "http://batdongsan.com.vn/ban-nha-mat-pho/p8/ban-nha-mat-pho-duong-2-cu-xa-do-thanh-phuong-4-12/tien-so-cx-quan-3-dt-3xm-pr8549295",
  "propertyName": "Bùi Minh Tuấn",
  "propertyId": 0,
  "propertyPrice": "12.5 tỷ ",
  "propertyPhone": "0916633379",
  "propertyTitle": "Bán nhà mặt tiền đường số 2 Cư Xá Đô Thành, quận 3, DT 4,3x22m"
}