{
  "propertyGroup": 1,
  "propertyUrl": "http://batdongsan.com.vn/ban-nha-mat-pho/p7/ban-nha-mat-pho-duong-nguyen-van-huyen-phuong-quan-hoa/gap-moi-dep-so-do-chinh-chu-tai-37-cau-giay-ha-noi-pr8601851",
  "propertyDescription": "Bán gấp nhà mặt phố sổ đỏ chính chủ tại 37 Nguyễn Văn Huyên, Cầu Giấy, Hà Nội. Diện tích 70m2, mặt tiền 5.55m. Đất vuông vắn, nhà hướng Tây. Nhà xây mới đẹp 6.5 tầng, kiến trúc hiện đại, xây dựng để ở nên rất chắc chắn, có thang máy (thang máy nhập khẩu). Vị trí nhà tại tuyến đường đẹp, tiện kinh doanh nhà hàng, spa, karaoke, văn phòng,... Giao thông đi lại thuận lợi, đường rộng 60m, vỉa hè 8m, có thể cho thuê giá cao. Giá bán 28.5 tỷ Liên hệ chính chủ cô Oanh 01669797686",
  "propertyAddress": "Đường Nguyễn Văn Huyên, Phường Quan Hoa, Cầu Giấy, Hà Nội",
  "propertyName": "cô Oanh",
  "propertyMobile": "01669797686",
  "propertySquare": "70m²",
  "propertyExpired": "07-02-2016",
  "propertyId": 0,
  "propertyPrice": "28.5 tỷ ",
  "propertyPosted": "07-01-2016",
  "propertyTitle": "Bán gấp nhà mặt phố mới đẹp, sổ đỏ chính chủ tại 37 Nguyễn Văn Huyên, Cầu Giấy, Hà Nội"
}