{
  "propertyGroup": 1,
  "propertyDescription": "Cần bán gấp nhà căn góc 2MT đường C1, Cộng Hòa, 1 lầu, 1 lửng, ST, 3PN, DT 29m2, DTSD 54m2. Cách MT đường Cộng Hòa 100m, gần trường học, gần siêu thị, giao thông thuận tiện đi lại, an ninh, tiện buôn bán kinh doanh mọi ngành nghề. Nhà hiện đang kinh doanh Cafe. Hướng ĐN. Giá 2,45 tỷ TL. Liên hệ xem nhà Anh Hoàng 0918987698. Nhận ký gửi mua bán bất động sản nhà phố các quận trung tâm, hỗ trợ thủ tục pháp lý, vay vốn NH.",
  "propertyAddress": "Đường C1, Tân Bình, Hồ Chí Minh",
  "propertyMobile": "0909546839",
  "propertySquare": "29m²",
  "propertyExpired": "19-01-2016",
  "propertyEmail": "phamthanhsang456@gmail.com",
  "propertyPosted": "12-01-2016",
  "propertyUrl": "http://batdongsan.com.vn/ban-nha-mat-pho/p24/ban-nha-mat-pho-duong-c1-phuong-13-10/can-gap-can-goc-2mt-cong-hoa-1l-1-lung-dt-29m2-gia-2-45-ty-pr8626572",
  "propertyName": "Phạm Thành Sang",
  "propertyId": 0,
  "propertyPrice": "2.45 tỷ ",
  "propertyPhone": "0909546839",
  "propertyTitle": "Cần bán gấp nhà căn góc 2MT đường C1, Cộng Hòa, 1L, 1 lửng, DT 29m2, giá 2,45 tỷ"
}