{
  "propertyGroup": 1,
  "propertyDescription": "Cần tiền nên bán gấp nhà mặt tiền Nguyễn Thị Thập, nhà xây dựng 5 lầu, DT 450m2, có thang máy, vị trí gần đường Nguyễn Văn Linh, chợ Tân Mỹ, rất thích hợp mở văn phòng hoặc cho thuê. Giá bán 10,7 tỷ. Liên hệ xem nhà và vị trí: 0916550101 - 0988.555.551 Hưng.",
  "propertyAddress": "Đường Nguyễn Thị Thập, Quận 7, Hồ Chí Minh",
  "propertyMobile": "0988555551",
  "propertySquare": "450m²",
  "propertyExpired": "21-01-2016",
  "propertyEmail": "hung.newhouse@gmail.com",
  "propertyPosted": "14-01-2016",
  "propertyUrl": "http://batdongsan.com.vn/ban-nha-mat-pho/p17/ban-nha-mat-pho-duong-nguyen-thi-thap-59/tien-5-lau-dt-450m-co-thang-may-10-7-ty-xem-0916550101-pr8640731",
  "propertyName": "Đặng Thanh Hưng",
  "propertyId": 0,
  "propertyPrice": "10.7 tỷ ",
  "propertyPhone": "0988555551",
  "propertyTitle": "Bán nhà mặt tiền đường Nguyễn Thị Thập, 5 lầu, DT 450m2 có thang máy, 10,7 tỷ. Xem nhà: 0916550101"
}